{
  "slug": "world-traveler",
  "fields": [
    {
      "id": "h1_your_favorite_country_in_poster_",
      "type": "text",
      "label": "H1 — Your favorite country, in poster form.",
      "default": "Your favorite country, in poster form."
    },
    {
      "id": "h2_explore_countries",
      "type": "text",
      "label": "H2 — Explore Countries",
      "default": "Explore Countries"
    },
    {
      "id": "h2_poster_collection",
      "type": "text",
      "label": "H2 — Poster Collection",
      "default": "Poster Collection"
    },
    {
      "id": "h2_postcard_layouts",
      "type": "text",
      "label": "H2 — Postcard Layouts",
      "default": "Postcard Layouts"
    },
    {
      "id": "h2_what_creators_say",
      "type": "text",
      "label": "H2 — What Creators Say",
      "default": "What Creators Say"
    },
    {
      "id": "h2_turn_travel_into_a_collectible",
      "type": "text",
      "label": "H2 — Turn travel into a collectible.",
      "default": "Turn travel into a collectible."
    },
    {
      "id": "button_choose_starter",
      "type": "text",
      "label": "Button — Choose Starter",
      "default": "Choose Starter"
    },
    {
      "id": "button_get_full_collection",
      "type": "text",
      "label": "Button — Get Full Collection",
      "default": "Get Full Collection"
    },
    {
      "id": "link_passportposters_co",
      "type": "text",
      "label": "Link — ✦ PassportPosters Co.",
      "default": "✦ PassportPosters Co."
    },
    {
      "id": "link_home",
      "type": "text",
      "label": "Link — Home",
      "default": "Home"
    },
    {
      "id": "link_countries",
      "type": "text",
      "label": "Link — Countries",
      "default": "Countries"
    },
    {
      "id": "link_posters",
      "type": "text",
      "label": "Link — Posters",
      "default": "Posters"
    },
    {
      "id": "link_postcards",
      "type": "text",
      "label": "Link — Postcards",
      "default": "Postcards"
    },
    {
      "id": "link_reviews",
      "type": "text",
      "label": "Link — Reviews",
      "default": "Reviews"
    },
    {
      "id": "link_download",
      "type": "text",
      "label": "Link — Download",
      "default": "Download"
    },
    {
      "id": "link_get_the_collection",
      "type": "text",
      "label": "Link — Get the Collection",
      "default": "Get the Collection"
    },
    {
      "id": "link_browse_countries",
      "type": "text",
      "label": "Link — Browse Countries",
      "default": "Browse Countries"
    },
    {
      "id": "phone_0",
      "type": "tel",
      "label": "Phone",
      "default": "149397604037"
    },
    {
      "id": "phone_1",
      "type": "tel",
      "label": "Phone",
      "default": "151854841997"
    },
    {
      "id": "phone_2",
      "type": "tel",
      "label": "Phone",
      "default": "150260289865"
    },
    {
      "id": "phone_3",
      "type": "tel",
      "label": "Phone",
      "default": "1552832230"
    },
    {
      "id": "phone_4",
      "type": "tel",
      "label": "Phone",
      "default": "148079692742"
    },
    {
      "id": "phone_5",
      "type": "tel",
      "label": "Phone",
      "default": "151648363826"
    },
    {
      "id": "phone_6",
      "type": "tel",
      "label": "Phone",
      "default": "148372955844"
    },
    {
      "id": "phone_7",
      "type": "tel",
      "label": "Phone",
      "default": "151863815034"
    },
    {
      "id": "phone_8",
      "type": "tel",
      "label": "Phone",
      "default": "148573842297"
    },
    {
      "id": "phone_9",
      "type": "tel",
      "label": "Phone",
      "default": "152818130480"
    },
    {
      "id": "phone_10",
      "type": "tel",
      "label": "Phone",
      "default": "152816434470"
    },
    {
      "id": "phone_11",
      "type": "tel",
      "label": "Phone",
      "default": "5-4754268700"
    },
    {
      "id": "phone_12",
      "type": "tel",
      "label": "Phone",
      "default": "153305048729"
    },
    {
      "id": "phone_13",
      "type": "tel",
      "label": "Phone",
      "default": "150421420869"
    },
    {
      "id": "phone_14",
      "type": "tel",
      "label": "Phone",
      "default": "153435159066"
    },
    {
      "id": "image_0",
      "type": "image",
      "label": "Image 1",
      "default": "https://images.unsplash.com/photo-1493976040374-85c8e12f0c0e?w=400&amp;h=533&amp;fit=crop"
    },
    {
      "id": "image_1",
      "type": "image",
      "label": "Image 2",
      "default": "https://images.unsplash.com/photo-1518548419970-58e3b4079ab2?w=400&amp;h=533&amp;fit=crop"
    },
    {
      "id": "image_2",
      "type": "image",
      "label": "Image 3",
      "default": "https://images.unsplash.com/photo-1502602898657-3e91760cbb34?w=400&amp;h=533&amp;fit=crop"
    },
    {
      "id": "image_3",
      "type": "image",
      "label": "Image 4",
      "default": "https://images.unsplash.com/photo-1552832230-c0197dd311b5?w=400&amp;h=533&amp;fit=crop"
    },
    {
      "id": "image_4",
      "type": "image",
      "label": "Image 5",
      "default": "https://images.unsplash.com/photo-1480796927426-f609979314bd?w=500&amp;h=667&amp;fit=crop"
    },
    {
      "id": "image_5",
      "type": "image",
      "label": "Image 6",
      "default": "https://images.unsplash.com/photo-1516483638261-f4dbaf036963?w=500&amp;h=667&amp;fit=crop"
    },
    {
      "id": "image_6",
      "type": "image",
      "label": "Image 7",
      "default": "https://images.unsplash.com/photo-1483729558449-99ef09a8c325?w=500&amp;h=667&amp;fit=crop"
    },
    {
      "id": "image_7",
      "type": "image",
      "label": "Image 8",
      "default": "${c.img}"
    },
    {
      "id": "image_8",
      "type": "image",
      "label": "Image 9",
      "default": "${p.front}"
    }
  ]
}
