{
  "slug": "gift-giving-surprise",
  "fields": [
    {
      "id": "h1_send_a_surprise_make_it_a_moment",
      "type": "text",
      "label": "H1 — Send a surprise. Make it a moment.",
      "default": "Send a surprise. Make it a moment."
    },
    {
      "id": "h2_four_steps_to_wow",
      "type": "text",
      "label": "H2 — Four steps to wow.",
      "default": "Four steps to wow."
    },
    {
      "id": "h2_every_occasion_covered",
      "type": "text",
      "label": "H2 — Every occasion. Covered.",
      "default": "Every occasion. Covered."
    },
    {
      "id": "h2_see_the_magic",
      "type": "text",
      "label": "H2 — See the magic.",
      "default": "See the magic."
    },
    {
      "id": "h2_people_are_losing_it",
      "type": "text",
      "label": "H2 — People are losing it.",
      "default": "People are losing it."
    },
    {
      "id": "h2_make_gifting_fun_again",
      "type": "text",
      "label": "H2 — Make gifting fun again.",
      "default": "Make gifting fun again."
    },
    {
      "id": "h3_choose_a_theme",
      "type": "text",
      "label": "H3 — Choose a Theme",
      "default": "Choose a Theme"
    },
    {
      "id": "h3_personalize",
      "type": "text",
      "label": "H3 — Personalize",
      "default": "Personalize"
    },
    {
      "id": "h3_send_the_link",
      "type": "text",
      "label": "H3 — Send the Link",
      "default": "Send the Link"
    },
    {
      "id": "h3_they_unlock",
      "type": "text",
      "label": "H3 — They Unlock",
      "default": "They Unlock"
    },
    {
      "id": "button_watch_a_reveal",
      "type": "text",
      "label": "Button — Watch a Reveal",
      "default": "Watch a Reveal"
    },
    {
      "id": "button_go",
      "type": "text",
      "label": "Button — Go",
      "default": "Go"
    },
    {
      "id": "button_submit",
      "type": "text",
      "label": "Button — Submit",
      "default": "Submit"
    },
    {
      "id": "link_vaultpop",
      "type": "text",
      "label": "Link — VAULTPOP",
      "default": "VAULTPOP"
    },
    {
      "id": "link_home",
      "type": "text",
      "label": "Link — Home",
      "default": "Home"
    },
    {
      "id": "link_how_it_works",
      "type": "text",
      "label": "Link — How It Works",
      "default": "How It Works"
    },
    {
      "id": "link_drop_themes",
      "type": "text",
      "label": "Link — Drop Themes",
      "default": "Drop Themes"
    },
    {
      "id": "link_preview",
      "type": "text",
      "label": "Link — Preview",
      "default": "Preview"
    },
    {
      "id": "link_reviews",
      "type": "text",
      "label": "Link — Reviews",
      "default": "Reviews"
    },
    {
      "id": "link_get_the_vault",
      "type": "text",
      "label": "Link — Get the Vault",
      "default": "Get the Vault"
    }
  ]
}
