{
  "slug": "ceramic-factory",
  "fields": [
    {
      "id": "h1_your_favorite_mug_upgraded",
      "type": "text",
      "label": "H1 — Your favorite mug, upgraded.",
      "default": "Your favorite mug, upgraded."
    },
    {
      "id": "h2_the_earth_collection",
      "type": "text",
      "label": "H2 — The Earth Collection",
      "default": "The Earth Collection"
    },
    {
      "id": "h2_made_with_patience",
      "type": "text",
      "label": "H2 — Made with patience",
      "default": "Made with patience"
    },
    {
      "id": "h2_where_clay_becomes_ceremony",
      "type": "text",
      "label": "H2 — Where clay becomes ceremony",
      "default": "Where clay becomes ceremony"
    },
    {
      "id": "h2_what_people_say",
      "type": "text",
      "label": "H2 — What people say",
      "default": "What people say"
    },
    {
      "id": "h2_own_a_piece_of_the_studio",
      "type": "text",
      "label": "H2 — Own a piece of the studio.",
      "default": "Own a piece of the studio."
    },
    {
      "id": "h3_p_name",
      "type": "text",
      "label": "H3 — ${p.name}",
      "default": "${p.name}"
    },
    {
      "id": "button_247",
      "type": "text",
      "label": "Button — 247",
      "default": "247"
    },
    {
      "id": "button_38",
      "type": "text",
      "label": "Button — 38",
      "default": "38"
    },
    {
      "id": "link_kilnkissed",
      "type": "text",
      "label": "Link — KilnKissed",
      "default": "KilnKissed"
    },
    {
      "id": "link_home",
      "type": "text",
      "label": "Link — Home",
      "default": "Home"
    },
    {
      "id": "link_new_drop",
      "type": "text",
      "label": "Link — New Drop",
      "default": "New Drop"
    },
    {
      "id": "link_pieces",
      "type": "text",
      "label": "Link — Pieces",
      "default": "Pieces"
    },
    {
      "id": "link_studio",
      "type": "text",
      "label": "Link — Studio",
      "default": "Studio"
    },
    {
      "id": "link_reviews",
      "type": "text",
      "label": "Link — Reviews",
      "default": "Reviews"
    },
    {
      "id": "link_buy_now",
      "type": "text",
      "label": "Link — Buy Now",
      "default": "Buy Now"
    },
    {
      "id": "link_shop_the_drop",
      "type": "text",
      "label": "Link — Shop the Drop",
      "default": "Shop the Drop"
    },
    {
      "id": "link_see_pieces",
      "type": "text",
      "label": "Link — See Pieces",
      "default": "See Pieces"
    },
    {
      "id": "phone_0",
      "type": "tel",
      "label": "Phone",
      "default": "156519356617"
    },
    {
      "id": "phone_1",
      "type": "tel",
      "label": "Phone",
      "default": "157874955656"
    },
    {
      "id": "phone_2",
      "type": "tel",
      "label": "Phone",
      "default": "161070159600"
    },
    {
      "id": "phone_3",
      "type": "tel",
      "label": "Phone",
      "default": "149310664151"
    },
    {
      "id": "phone_4",
      "type": "tel",
      "label": "Phone",
      "default": "152597313221"
    },
    {
      "id": "phone_5",
      "type": "tel",
      "label": "Phone",
      "default": "1556036518"
    },
    {
      "id": "phone_6",
      "type": "tel",
      "label": "Phone",
      "default": "151422874258"
    },
    {
      "id": "image_0",
      "type": "image",
      "label": "Image 1",
      "default": "https://images.unsplash.com/photo-1565193566173-7a0ee3dbe261?w=1400&amp;q=80"
    },
    {
      "id": "image_1",
      "type": "image",
      "label": "Image 2",
      "default": "https://images.unsplash.com/photo-1578749556568-bc2c40e68b61?w=800&amp;q=80"
    },
    {
      "id": "image_2",
      "type": "image",
      "label": "Image 3",
      "default": "https://images.unsplash.com/photo-1610701596007-11502861dcfa?w=600&amp;q=80"
    },
    {
      "id": "image_3",
      "type": "image",
      "label": "Image 4",
      "default": "https://images.unsplash.com/photo-1493106641515-6b5631de4bb9?w=600&amp;q=80"
    },
    {
      "id": "image_4",
      "type": "image",
      "label": "Image 5",
      "default": "https://images.unsplash.com/photo-1525973132219-a04d4127e6e6?w=600&amp;q=80"
    },
    {
      "id": "image_5",
      "type": "image",
      "label": "Image 6",
      "default": "https://images.unsplash.com/photo-1556036518-6a2071ab9f44?w=700&amp;q=80"
    },
    {
      "id": "image_6",
      "type": "image",
      "label": "Image 7",
      "default": "${p.img}"
    }
  ]
}
